xter
