Metadata-Version: 1.1
Name: xter
Version: 1.0.0
Summary: Executor for commands from the Commander API.
Home-page: UNKNOWN
Author: www.itscoding.ch
Author-email: simon.d.mueller@gmail.com
License: MIT
Keywords: commander client,executor itscoding
Platform: UNKNOWN
Classifier: Development Status :: 4 - Beta
Classifier: Intended Audience :: Developers
Classifier: Programming Language :: Python :: 2.7
